{
    "data": {
        "location": "Hassan",
        "createdAt": "2022-07-29T04:25:39.351Z",
        "_id": "doc1",
        "firstName": "31653135313163353965363437396130:5cc8e394cdcef021dde878d2529e2bcf",
        "lastName": "31653135313163353965363437396130:3893fffc2904b5750a72ae9732de6bc8",
        "problem": [],
        "test": [],
        "updatedAt": "2022-07-29T04:25:51.037Z",
        "__v": 0,
        "review": [
            {
                "_id": "62e411d31baf9c0f5df83857",
                "reviewDescription": "Lorem Ipsum isafkghshgodjgsjdglsdjgdsjgsjgspgjsgjs;pgjs;gjspgjgojgodsjgsjdgjg simply dummy text of the printing and typesetting industry. Lorem Ipsum has been the industry's standard dummy text ever since the 1500s, when an unknown printer took a galley of type and scrambled it to make a type specimen book.",
                "reviewRating": 2,
                "reviewedUserName": "Manoj H R",
                "reviewedUserMail": "manu.hr1701@gmail.com",
                "reviewedDate": "2022-07-29T16:58:59.946Z",
                "comments": [
                    {
                        "_id": "62e412916cdd6410491f725d",
                        "commentDescription": "commentDescription",
                        "commentedUserId": "user231",
                        "commentedUserName": "manu",
                        "commentedUserMail": "manu@gmail.com",
                        "commentedDate": "2022-07-29T17:02:09.304Z"
                    },
                    {
                        "_id": "62e412c16cdd6410491f7260",
                        "commentDescription": "2nd Comment",
                        "commentedUserId": "user231",
                        "commentedUserName": "manoj Kumar",
                        "commentedUserMail": "manu1234@gmail.com",
                        "commentedDate": "2022-07-29T17:02:57.506Z"
                    }
                ]
            }
        ],
        "availability": []
    },
    "status": 200,
    "type": "success",
    "message": "Ok"
}